asynckraken/__init__.py
asynckraken/auth.py
asynckraken/client.py
asynckraken/types.py
asynckraken/version.py
asynckraken-0.1.3.dist-info/DESCRIPTION.rst
asynckraken-0.1.3.dist-info/METADATA
asynckraken-0.1.3.dist-info/RECORD
asynckraken-0.1.3.dist-info/WHEEL
asynckraken-0.1.3.dist-info/metadata.json
asynckraken-0.1.3.dist-info/top_level.txt
