Metadata-Version: 2.0
Name: asynckraken
Version: 0.1.3
Summary: kraken.com cryptocurrency exchange API
Home-page: https://github.com/drootnar/asynckraken
Author: Kamil Rogalski
Author-email: kamil.rogalski@pragmaticcoders.com
License: UNKNOWN
Platform: UNKNOWN
Classifier: Programming Language :: Python :: 3
Requires-Dist: aiohttp (==2.2.0)
